huaweicloudsdkcodecheck/__init__.py
huaweicloudsdkcodecheck/v2/__init__.py
huaweicloudsdkcodecheck/v2/codecheck_async_client.py
huaweicloudsdkcodecheck/v2/codecheck_client.py
huaweicloudsdkcodecheck/v2/model/__init__.py
huaweicloudsdkcodecheck/v2/model/check_config_info.py
huaweicloudsdkcodecheck/v2/model/check_parameters_request.py
huaweicloudsdkcodecheck/v2/model/check_parameters_response.py
huaweicloudsdkcodecheck/v2/model/check_record_data_info.py
huaweicloudsdkcodecheck/v2/model/check_record_issue_counts_info.py
huaweicloudsdkcodecheck/v2/model/check_record_request.py
huaweicloudsdkcodecheck/v2/model/check_record_response.py
huaweicloudsdkcodecheck/v2/model/check_ruleset_parameters_request.py
huaweicloudsdkcodecheck/v2/model/check_ruleset_parameters_response.py
huaweicloudsdkcodecheck/v2/model/config_task_parameter_body.py
huaweicloudsdkcodecheck/v2/model/create_ruleset_request.py
huaweicloudsdkcodecheck/v2/model/create_ruleset_response.py
huaweicloudsdkcodecheck/v2/model/create_task_request.py
huaweicloudsdkcodecheck/v2/model/create_task_request_v2.py
huaweicloudsdkcodecheck/v2/model/create_task_response.py
huaweicloudsdkcodecheck/v2/model/custom_attributes.py
huaweicloudsdkcodecheck/v2/model/custom_attributes_rule.py
huaweicloudsdkcodecheck/v2/model/defect_events.py
huaweicloudsdkcodecheck/v2/model/defect_fragment_v2.py
huaweicloudsdkcodecheck/v2/model/defect_info_v2.py
huaweicloudsdkcodecheck/v2/model/delete_ruleset_request.py
huaweicloudsdkcodecheck/v2/model/delete_ruleset_response.py
huaweicloudsdkcodecheck/v2/model/delete_task_request.py
huaweicloudsdkcodecheck/v2/model/delete_task_response.py
huaweicloudsdkcodecheck/v2/model/ignore_path_setting_item.py
huaweicloudsdkcodecheck/v2/model/inc_config_v2.py
huaweicloudsdkcodecheck/v2/model/list_rules_request.py
huaweicloudsdkcodecheck/v2/model/list_rules_response.py
huaweicloudsdkcodecheck/v2/model/list_rulesets_request.py
huaweicloudsdkcodecheck/v2/model/list_rulesets_response.py
huaweicloudsdkcodecheck-3.1.46.dist-info/LICENSE
huaweicloudsdkcodecheck-3.1.46.dist-info/METADATA
huaweicloudsdkcodecheck-3.1.46.dist-info/WHEEL
huaweicloudsdkcodecheck-3.1.46.dist-info/top_level.txt
huaweicloudsdkcodecheck-3.1.46.dist-info/RECORD
